properties/__init__.py
properties/__main__.py
properties/decoder.py
properties/encoder.py
properties/functional.py
properties/properties.py
properties_py-1.2.1.dist-info/LICENSE
properties_py-1.2.1.dist-info/METADATA
properties_py-1.2.1.dist-info/WHEEL
properties_py-1.2.1.dist-info/RECORD
